README.md
setup.py
ta3ta2_api/__init__.py
ta3ta2_api/core_pb2.py
ta3ta2_api/core_pb2_grpc.py
ta3ta2_api/pipeline_pb2.py
ta3ta2_api/pipeline_pb2_grpc.py
ta3ta2_api/primitive_pb2.py
ta3ta2_api/primitive_pb2_grpc.py
ta3ta2_api/problem_pb2.py
ta3ta2_api/problem_pb2_grpc.py
ta3ta2_api/utils.py
ta3ta2_api/value_pb2.py
ta3ta2_api/value_pb2_grpc.py
ta3ta2_api.egg-info/PKG-INFO
ta3ta2_api.egg-info/SOURCES.txt
ta3ta2_api.egg-info/dependency_links.txt
ta3ta2_api.egg-info/requires.txt
ta3ta2_api.egg-info/top_level.txt