Metadata-Version: 2.1
Name: ta3ta2-api
Version: 2020.6.2
Summary: GRPC protocol for the TA3-TA2 communication API.
Home-page: https://gitlab.com/datadrivendiscovery/ta3ta2-api
Author: DARPA D3M Program
License: Apache-2.0
Platform: UNKNOWN
Classifier: License :: OSI Approved :: Apache Software License
